onnx_graphsurgeon/__init__.py
onnx_graphsurgeon/exporters/__init__.py
onnx_graphsurgeon/exporters/base_exporter.py
onnx_graphsurgeon/exporters/onnx_exporter.py
onnx_graphsurgeon/graph_pattern/__init__.py
onnx_graphsurgeon/graph_pattern/graph_pattern.py
onnx_graphsurgeon/importers/__init__.py
onnx_graphsurgeon/importers/base_importer.py
onnx_graphsurgeon/importers/onnx_importer.py
onnx_graphsurgeon/ir/__init__.py
onnx_graphsurgeon/ir/function.py
onnx_graphsurgeon/ir/graph.py
onnx_graphsurgeon/ir/node.py
onnx_graphsurgeon/ir/tensor.py
onnx_graphsurgeon/logger/__init__.py
onnx_graphsurgeon/logger/logger.py
onnx_graphsurgeon/util/__init__.py
onnx_graphsurgeon/util/exception.py
onnx_graphsurgeon/util/misc.py
onnx_graphsurgeon-0.5.8.dist-info/LICENSE
onnx_graphsurgeon-0.5.8.dist-info/METADATA
onnx_graphsurgeon-0.5.8.dist-info/WHEEL
onnx_graphsurgeon-0.5.8.dist-info/top_level.txt
onnx_graphsurgeon-0.5.8.dist-info/zip-safe
onnx_graphsurgeon-0.5.8.dist-info/RECORD
