Metadata-Version: 2.1
Name: onnx_graphsurgeon
Version: 0.5.8
Summary: ONNX GraphSurgeon
Home-page: https://github.com/NVIDIA/TensorRT/tree/main/tools/onnx-graphsurgeon
Author: NVIDIA
Author-email: svc_tensorrt@nvidia.com
License: Apache 2.0
Classifier: Intended Audience :: Developers
Classifier: Programming Language :: Python :: 3
License-File: LICENSE
Requires-Dist: numpy
Requires-Dist: onnx (>=1.14.0)
